[
  {
    "id": "SMCI-1770631674",
    "ticker": "SMCI",
    "name": "SMCI",
    "strategy": "골든크로스 (Trend)",
    "price": 34.38,
    "change_pct": 11.44,
    "sentiment": "BULLISH",
    "impact_score": 93,
    "target_price": 39.54,
    "stop_loss": 31.63,
    "ai_reason": "5일 이동평균선이 20일선을 돌파하며 강력한 상승 추세로 진입했습니다.",
    "technical_analysis": "기술적 지표상 RSI는 54.9로 안정권에 위치하며, 1차 지지선 $32.66 상단에서 강한 하방 경직성을 확보했습니다.",
    "fundamental_analysis": "Stock Empire 실시간 감시 엔진이 SMCI의 수급 변화를 포착했습니다. 현재 골든크로스 (Trend) 전략 기반 유의미한 시그널이 발생한 상태입니다.",
    "action_plan": "단기 목표가 $39.54 도달 시 분할 익절, $31.63 이탈 시 선제적 리스크 관리를 권장합니다.",
    "is_real_time": true,
    "source": "Stock Empire Stealth AI",
    "updated_at": "2026-02-09T10:07:54.586369"
  },
  {
    "id": "SOFI-1770631675",
    "ticker": "SOFI",
    "name": "SOFI",
    "strategy": "RSI 반등 (Oversold)",
    "price": 20.86,
    "change_pct": 7.19,
    "sentiment": "BULLISH",
    "impact_score": 93,
    "target_price": 23.99,
    "stop_loss": 19.19,
    "ai_reason": "RSI 수치가 21.6로 과매도 구간입니다. 단기 반등 확률이 매우 높습니다.",
    "technical_analysis": "기술적 지표상 RSI는 21.6로 과매도권에 위치하며, 1차 지지선 $19.82 상단에서 강한 하방 경직성을 확보했습니다.",
    "fundamental_analysis": "Stock Empire 실시간 감시 엔진이 SOFI의 수급 변화를 포착했습니다. 현재 RSI 반등 (Oversold) 전략 기반 유의미한 시그널이 발생한 상태입니다.",
    "action_plan": "단기 목표가 $23.99 도달 시 분할 익절, $19.19 이탈 시 선제적 리스크 관리를 권장합니다.",
    "is_real_time": true,
    "source": "Stock Empire Stealth AI",
    "updated_at": "2026-02-09T10:07:55.893076"
  },
  {
    "id": "NFLX-1770631694",
    "ticker": "NFLX",
    "name": "NFLX",
    "strategy": "RSI 반등 (Oversold)",
    "price": 82.2,
    "change_pct": 1.64,
    "sentiment": "BULLISH",
    "impact_score": 93,
    "target_price": 94.53,
    "stop_loss": 75.62,
    "ai_reason": "RSI 수치가 32.0로 과매도 구간입니다. 단기 반등 확률이 매우 높습니다.",
    "technical_analysis": "기술적 지표상 RSI는 32.0로 과매도권에 위치하며, 1차 지지선 $78.09 상단에서 강한 하방 경직성을 확보했습니다.",
    "fundamental_analysis": "Stock Empire 실시간 감시 엔진이 NFLX의 수급 변화를 포착했습니다. 현재 RSI 반등 (Oversold) 전략 기반 유의미한 시그널이 발생한 상태입니다.",
    "action_plan": "단기 목표가 $94.53 도달 시 분할 익절, $75.62 이탈 시 선제적 리스크 관리를 권장합니다.",
    "is_real_time": true,
    "source": "Stock Empire Stealth AI",
    "updated_at": "2026-02-09T10:08:14.351997"
  },
  {
    "id": "COIN-1770631686",
    "ticker": "COIN",
    "name": "COIN",
    "strategy": "RSI 반등 (Oversold)",
    "price": 165.12,
    "change_pct": 13.0,
    "sentiment": "BULLISH",
    "impact_score": 90,
    "target_price": 189.89,
    "stop_loss": 151.91,
    "ai_reason": "RSI 수치가 16.7로 과매도 구간입니다. 단기 반등 확률이 매우 높습니다.",
    "technical_analysis": "기술적 지표상 RSI는 16.7로 과매도권에 위치하며, 1차 지지선 $156.86 상단에서 강한 하방 경직성을 확보했습니다.",
    "fundamental_analysis": "Stock Empire 실시간 감시 엔진이 COIN의 수급 변화를 포착했습니다. 현재 RSI 반등 (Oversold) 전략 기반 유의미한 시그널이 발생한 상태입니다.",
    "action_plan": "단기 목표가 $189.89 도달 시 분할 익절, $151.91 이탈 시 선제적 리스크 관리를 권장합니다.",
    "is_real_time": true,
    "source": "Stock Empire Stealth AI",
    "updated_at": "2026-02-09T10:08:06.493746"
  },
  {
    "id": "MSTR-1770631691",
    "ticker": "MSTR",
    "name": "MSTR",
    "strategy": "RSI 반등 (Oversold)",
    "price": 134.93,
    "change_pct": 26.11,
    "sentiment": "BULLISH",
    "impact_score": 90,
    "target_price": 155.17,
    "stop_loss": 124.14,
    "ai_reason": "RSI 수치가 34.0로 과매도 구간입니다. 단기 반등 확률이 매우 높습니다.",
    "technical_analysis": "기술적 지표상 RSI는 34.0로 과매도권에 위치하며, 1차 지지선 $128.18 상단에서 강한 하방 경직성을 확보했습니다.",
    "fundamental_analysis": "Stock Empire 실시간 감시 엔진이 MSTR의 수급 변화를 포착했습니다. 현재 RSI 반등 (Oversold) 전략 기반 유의미한 시그널이 발생한 상태입니다.",
    "action_plan": "단기 목표가 $155.17 도달 시 분할 익절, $124.14 이탈 시 선제적 리스크 관리를 권장합니다.",
    "is_real_time": true,
    "source": "Stock Empire Stealth AI",
    "updated_at": "2026-02-09T10:08:11.738286"
  },
  {
    "id": "MSFT-1770631683",
    "ticker": "MSFT",
    "name": "MSFT",
    "strategy": "RSI 반등 (Oversold)",
    "price": 401.14,
    "change_pct": 1.9,
    "sentiment": "BULLISH",
    "impact_score": 89,
    "target_price": 461.31,
    "stop_loss": 369.05,
    "ai_reason": "RSI 수치가 31.0로 과매도 구간입니다. 단기 반등 확률이 매우 높습니다.",
    "technical_analysis": "기술적 지표상 RSI는 31.0로 과매도권에 위치하며, 1차 지지선 $381.08 상단에서 강한 하방 경직성을 확보했습니다.",
    "fundamental_analysis": "Stock Empire 실시간 감시 엔진이 MSFT의 수급 변화를 포착했습니다. 현재 RSI 반등 (Oversold) 전략 기반 유의미한 시그널이 발생한 상태입니다.",
    "action_plan": "단기 목표가 $461.31 도달 시 분할 익절, $369.05 이탈 시 선제적 리스크 관리를 권장합니다.",
    "is_real_time": true,
    "source": "Stock Empire Stealth AI",
    "updated_at": "2026-02-09T10:08:03.880919"
  },
  {
    "id": "PLTR-1770631685",
    "ticker": "PLTR",
    "name": "PLTR",
    "strategy": "RSI 반등 (Oversold)",
    "price": 135.9,
    "change_pct": 4.53,
    "sentiment": "BULLISH",
    "impact_score": 88,
    "target_price": 156.28,
    "stop_loss": 125.03,
    "ai_reason": "RSI 수치가 27.5로 과매도 구간입니다. 단기 반등 확률이 매우 높습니다.",
    "technical_analysis": "기술적 지표상 RSI는 27.5로 과매도권에 위치하며, 1차 지지선 $129.1 상단에서 강한 하방 경직성을 확보했습니다.",
    "fundamental_analysis": "Stock Empire 실시간 감시 엔진이 PLTR의 수급 변화를 포착했습니다. 현재 RSI 반등 (Oversold) 전략 기반 유의미한 시그널이 발생한 상태입니다.",
    "action_plan": "단기 목표가 $156.28 도달 시 분할 익절, $125.03 이탈 시 선제적 리스크 관리를 권장합니다.",
    "is_real_time": true,
    "source": "Stock Empire Stealth AI",
    "updated_at": "2026-02-09T10:08:05.188820"
  },
  {
    "id": "RIOT-1770631681",
    "ticker": "RIOT",
    "name": "RIOT",
    "strategy": "RSI 반등 (Oversold)",
    "price": 14.45,
    "change_pct": 19.82,
    "sentiment": "BULLISH",
    "impact_score": 86,
    "target_price": 16.62,
    "stop_loss": 13.29,
    "ai_reason": "RSI 수치가 31.1로 과매도 구간입니다. 단기 반등 확률이 매우 높습니다.",
    "technical_analysis": "기술적 지표상 RSI는 31.1로 과매도권에 위치하며, 1차 지지선 $13.73 상단에서 강한 하방 경직성을 확보했습니다.",
    "fundamental_analysis": "Stock Empire 실시간 감시 엔진이 RIOT의 수급 변화를 포착했습니다. 현재 RSI 반등 (Oversold) 전략 기반 유의미한 시그널이 발생한 상태입니다.",
    "action_plan": "단기 목표가 $16.62 도달 시 분할 익절, $13.29 이탈 시 선제적 리스크 관리를 권장합니다.",
    "is_real_time": true,
    "source": "Stock Empire Stealth AI",
    "updated_at": "2026-02-09T10:08:01.249880"
  },
  {
    "id": "MARA-1770631693",
    "ticker": "MARA",
    "name": "MARA",
    "strategy": "RSI 반등 (Oversold)",
    "price": 8.24,
    "change_pct": 22.44,
    "sentiment": "BULLISH",
    "impact_score": 85,
    "target_price": 9.48,
    "stop_loss": 7.58,
    "ai_reason": "RSI 수치가 30.5로 과매도 구간입니다. 단기 반등 확률이 매우 높습니다.",
    "technical_analysis": "기술적 지표상 RSI는 30.5로 과매도권에 위치하며, 1차 지지선 $7.83 상단에서 강한 하방 경직성을 확보했습니다.",
    "fundamental_analysis": "Stock Empire 실시간 감시 엔진이 MARA의 수급 변화를 포착했습니다. 현재 RSI 반등 (Oversold) 전략 기반 유의미한 시그널이 발생한 상태입니다.",
    "action_plan": "단기 목표가 $9.48 도달 시 분할 익절, $7.58 이탈 시 선제적 리스크 관리를 권장합니다.",
    "is_real_time": true,
    "source": "Stock Empire Stealth AI",
    "updated_at": "2026-02-09T10:08:13.042067"
  },
  {
    "id": "AMD-1770631679",
    "ticker": "AMD",
    "name": "AMD",
    "strategy": "추세 지속 (Neutral)",
    "price": 208.44,
    "change_pct": 8.28,
    "sentiment": "BULLISH",
    "impact_score": 74,
    "target_price": 239.71,
    "stop_loss": 191.76,
    "ai_reason": "현재 안정적인 흐름을 유지 중이며, 큰 변동성 시그널은 포착되지 않았습니다.",
    "technical_analysis": "기술적 지표상 RSI는 41.2로 안정권에 위치하며, 1차 지지선 $198.02 상단에서 강한 하방 경직성을 확보했습니다.",
    "fundamental_analysis": "Stock Empire 실시간 감시 엔진이 AMD의 수급 변화를 포착했습니다. 현재 추세 지속 (Neutral) 전략 기반 유의미한 시그널이 발생한 상태입니다.",
    "action_plan": "단기 목표가 $239.71 도달 시 분할 익절, $191.76 이탈 시 선제적 리스크 관리를 권장합니다.",
    "is_real_time": true,
    "source": "Stock Empire Stealth AI",
    "updated_at": "2026-02-09T10:07:59.845773"
  },
  {
    "id": "AAPL-1770631673",
    "ticker": "AAPL",
    "name": "AAPL",
    "strategy": "추세 지속 (Neutral)",
    "price": 278.12,
    "change_pct": 0.8,
    "sentiment": "BULLISH",
    "impact_score": 72,
    "target_price": 319.84,
    "stop_loss": 255.87,
    "ai_reason": "현재 안정적인 흐름을 유지 중이며, 큰 변동성 시그널은 포착되지 않았습니다.",
    "technical_analysis": "기술적 지표상 RSI는 74.2로 과열권에 위치하며, 1차 지지선 $264.21 상단에서 강한 하방 경직성을 확보했습니다.",
    "fundamental_analysis": "Stock Empire 실시간 감시 엔진이 AAPL의 수급 변화를 포착했습니다. 현재 추세 지속 (Neutral) 전략 기반 유의미한 시그널이 발생한 상태입니다.",
    "action_plan": "단기 목표가 $319.84 도달 시 분할 익절, $255.87 이탈 시 선제적 리스크 관리를 권장합니다.",
    "is_real_time": true,
    "source": "Stock Empire Stealth AI",
    "updated_at": "2026-02-09T10:07:53.274831"
  },
  {
    "id": "PATH-1770631689",
    "ticker": "PATH",
    "name": "PATH",
    "strategy": "추세 지속 (Neutral)",
    "price": 12.89,
    "change_pct": 6.71,
    "sentiment": "BULLISH",
    "impact_score": 72,
    "target_price": 14.82,
    "stop_loss": 11.86,
    "ai_reason": "현재 안정적인 흐름을 유지 중이며, 큰 변동성 시그널은 포착되지 않았습니다.",
    "technical_analysis": "기술적 지표상 RSI는 37.1로 안정권에 위치하며, 1차 지지선 $12.25 상단에서 강한 하방 경직성을 확보했습니다.",
    "fundamental_analysis": "Stock Empire 실시간 감시 엔진이 PATH의 수급 변화를 포착했습니다. 현재 추세 지속 (Neutral) 전략 기반 유의미한 시그널이 발생한 상태입니다.",
    "action_plan": "단기 목표가 $14.82 도달 시 분할 익절, $11.86 이탈 시 선제적 리스크 관리를 권장합니다.",
    "is_real_time": true,
    "source": "Stock Empire Stealth AI",
    "updated_at": "2026-02-09T10:08:09.122813"
  },
  {
    "id": "TSLA-1770631678",
    "ticker": "TSLA",
    "name": "TSLA",
    "strategy": "추세 지속 (Neutral)",
    "price": 411.11,
    "change_pct": 3.5,
    "sentiment": "BULLISH",
    "impact_score": 67,
    "target_price": 472.78,
    "stop_loss": 378.22,
    "ai_reason": "현재 안정적인 흐름을 유지 중이며, 큰 변동성 시그널은 포착되지 않았습니다.",
    "technical_analysis": "기술적 지표상 RSI는 40.8로 안정권에 위치하며, 1차 지지선 $390.55 상단에서 강한 하방 경직성을 확보했습니다.",
    "fundamental_analysis": "Stock Empire 실시간 감시 엔진이 TSLA의 수급 변화를 포착했습니다. 현재 추세 지속 (Neutral) 전략 기반 유의미한 시그널이 발생한 상태입니다.",
    "action_plan": "단기 목표가 $472.78 도달 시 분할 익절, $378.22 이탈 시 선제적 리스크 관리를 권장합니다.",
    "is_real_time": true,
    "source": "Stock Empire Stealth AI",
    "updated_at": "2026-02-09T10:07:58.539747"
  },
  {
    "id": "GOOGL-1770631682",
    "ticker": "GOOGL",
    "name": "GOOGL",
    "strategy": "추세 지속 (Neutral)",
    "price": 322.86,
    "change_pct": -2.53,
    "sentiment": "BEARISH",
    "impact_score": 66,
    "target_price": 297.03,
    "stop_loss": 339.0,
    "ai_reason": "현재 안정적인 흐름을 유지 중이며, 큰 변동성 시그널은 포착되지 않았습니다.",
    "technical_analysis": "기술적 지표상 RSI는 43.7로 안정권에 위치하며, 1차 지지선 $306.72 상단에서 강한 하방 경직성을 확보했습니다.",
    "fundamental_analysis": "Stock Empire 실시간 감시 엔진이 GOOGL의 수급 변화를 포착했습니다. 현재 추세 지속 (Neutral) 전략 기반 유의미한 시그널이 발생한 상태입니다.",
    "action_plan": "단기 목표가 $297.03 도달 시 분할 익절, $339.0 이탈 시 선제적 리스크 관리를 권장합니다.",
    "is_real_time": true,
    "source": "Stock Empire Stealth AI",
    "updated_at": "2026-02-09T10:08:02.556911"
  },
  {
    "id": "AI-1770631677",
    "ticker": "AI",
    "name": "AI",
    "strategy": "추세 지속 (Neutral)",
    "price": 11.65,
    "change_pct": 14.78,
    "sentiment": "BULLISH",
    "impact_score": 62,
    "target_price": 13.4,
    "stop_loss": 10.72,
    "ai_reason": "현재 안정적인 흐름을 유지 중이며, 큰 변동성 시그널은 포착되지 않았습니다.",
    "technical_analysis": "기술적 지표상 RSI는 40.9로 안정권에 위치하며, 1차 지지선 $11.07 상단에서 강한 하방 경직성을 확보했습니다.",
    "fundamental_analysis": "Stock Empire 실시간 감시 엔진이 AI의 수급 변화를 포착했습니다. 현재 추세 지속 (Neutral) 전략 기반 유의미한 시그널이 발생한 상태입니다.",
    "action_plan": "단기 목표가 $13.4 도달 시 분할 익절, $10.72 이탈 시 선제적 리스크 관리를 권장합니다.",
    "is_real_time": true,
    "source": "Stock Empire Stealth AI",
    "updated_at": "2026-02-09T10:07:57.233472"
  },
  {
    "id": "NVDA-1770631687",
    "ticker": "NVDA",
    "name": "NVDA",
    "strategy": "추세 지속 (Neutral)",
    "price": 185.41,
    "change_pct": 7.87,
    "sentiment": "BULLISH",
    "impact_score": 62,
    "target_price": 213.22,
    "stop_loss": 170.58,
    "ai_reason": "현재 안정적인 흐름을 유지 중이며, 큰 변동성 시그널은 포착되지 않았습니다.",
    "technical_analysis": "기술적 지표상 RSI는 49.3로 안정권에 위치하며, 1차 지지선 $176.14 상단에서 강한 하방 경직성을 확보했습니다.",
    "fundamental_analysis": "Stock Empire 실시간 감시 엔진이 NVDA의 수급 변화를 포착했습니다. 현재 추세 지속 (Neutral) 전략 기반 유의미한 시그널이 발생한 상태입니다.",
    "action_plan": "단기 목표가 $213.22 도달 시 분할 익절, $170.58 이탈 시 선제적 리스크 관리를 권장합니다.",
    "is_real_time": true,
    "source": "Stock Empire Stealth AI",
    "updated_at": "2026-02-09T10:08:07.818084"
  },
  {
    "id": "META-1770631690",
    "ticker": "META",
    "name": "META",
    "strategy": "추세 지속 (Neutral)",
    "price": 661.46,
    "change_pct": -1.31,
    "sentiment": "BEARISH",
    "impact_score": 61,
    "target_price": 608.54,
    "stop_loss": 694.53,
    "ai_reason": "현재 안정적인 흐름을 유지 중이며, 큰 변동성 시그널은 포착되지 않았습니다.",
    "technical_analysis": "기술적 지표상 RSI는 58.7로 안정권에 위치하며, 1차 지지선 $628.39 상단에서 강한 하방 경직성을 확보했습니다.",
    "fundamental_analysis": "Stock Empire 실시간 감시 엔진이 META의 수급 변화를 포착했습니다. 현재 추세 지속 (Neutral) 전략 기반 유의미한 시그널이 발생한 상태입니다.",
    "action_plan": "단기 목표가 $608.54 도달 시 분할 익절, $694.53 이탈 시 선제적 리스크 관리를 권장합니다.",
    "is_real_time": true,
    "source": "Stock Empire Stealth AI",
    "updated_at": "2026-02-09T10:08:10.429294"
  }
]